JupyterEarthTheme/__init__.py
JupyterEarthTheme/_version.py
jupyterearththeme-1.0.2.data/data/share/jupyter/labextensions/JupyterEarthTheme/package.json
jupyterearththeme-1.0.2.data/data/share/jupyter/labextensions/JupyterEarthTheme/static/509.af56cfa5ef6219bc58fd.js
jupyterearththeme-1.0.2.data/data/share/jupyter/labextensions/JupyterEarthTheme/static/remoteEntry.c91b26e7b603e62b1e0a.js
jupyterearththeme-1.0.2.data/data/share/jupyter/labextensions/JupyterEarthTheme/static/style.js
jupyterearththeme-1.0.2.data/data/share/jupyter/labextensions/JupyterEarthTheme/static/third-party-licenses.json
jupyterearththeme-1.0.2.data/data/share/jupyter/labextensions/JupyterEarthTheme/themes/JupyterEarthTheme/index.css
jupyterearththeme-1.0.2.data/data/share/jupyter/labextensions/JupyterEarthTheme/themes/JupyterEarthTheme/index.js
jupyterearththeme-1.0.2.data/data/share/jupyter/labextensions/JupyterEarthTheme/install.json
jupyterearththeme-1.0.2.dist-info/METADATA
jupyterearththeme-1.0.2.dist-info/WHEEL
jupyterearththeme-1.0.2.dist-info/licenses/LICENSE
jupyterearththeme-1.0.2.dist-info/RECORD
