Metadata-Version: 2.3
Name: JupyterEarthTheme
Version: 1.0.2
Summary: A JupyterLab/Notebook 7 theme.
Project-URL: Homepage, https://github.com/jantomec/JupyterEarthTheme
Project-URL: Bug Tracker, https://github.com/jantomec/JupyterEarthTheme/issues
Project-URL: Repository, https://github.com/jantomec/JupyterEarthTheme.git
Author-email: Jan Tomec <jan.tomec@gmail.com>
License: BSD 3-Clause License
License-File: LICENSE
Classifier: Framework :: Jupyter
Classifier: Framework :: Jupyter :: JupyterLab
Classifier: Framework :: Jupyter :: JupyterLab :: 4
Classifier: Framework :: Jupyter :: JupyterLab :: Extensions
Classifier: Framework :: Jupyter :: JupyterLab :: Extensions :: Prebuilt
Classifier: License :: OSI Approved :: BSD License
Classifier: Programming Language :: Python
Classifier: Programming Language :: Python :: 3
Classifier: Programming Language :: Python :: 3.8
Classifier: Programming Language :: Python :: 3.9
Classifier: Programming Language :: Python :: 3.10
Classifier: Programming Language :: Python :: 3.11
Classifier: Programming Language :: Python :: 3.12
Requires-Python: >=3.8
